src/__init__.py
src/core.py
src/events.py
src/exceptions.py
src/models.py
src/utils.py
carter_analytics_python_sdk-0.1.0.dist-info/LICENSE
carter_analytics_python_sdk-0.1.0.dist-info/METADATA
carter_analytics_python_sdk-0.1.0.dist-info/WHEEL
carter_analytics_python_sdk-0.1.0.dist-info/top_level.txt
carter_analytics_python_sdk-0.1.0.dist-info/RECORD
