Metadata-Version: 2.1
Name: carter-analytics-python-sdk
Version: 0.1.0
Summary: The Carter Analytics SDK is a powerful tool for tracking and analyzing user interactions in your Python applications. It provides a straightforward way to capture a wide range of events and send them to the Carter Analytics platform for processing and analysis.
Home-page: https://github.com/shyftlabs/carter-analytics-python-sdk
Classifier: Programming Language :: Python :: 3.11
Classifier: License :: OSI Approved :: MIT License
Classifier: Operating System :: OS Independent
Requires-Python: >=3.11
License-File: LICENSE
Requires-Dist: requests >=2.31.0
Requires-Dist: setuptools >=69.2.0
Requires-Dist: tenacity >=8.2.3
